Metadata-Version: 1.0
Name: farbox
Version: 0.0.1
Summary: FarBox
Home-page: UNKNOWN
Author: Hepochen
Author-email: hepochen@gmail.com
License: UNKNOWN
Platform: linux
